[
  {
    "name": "Application Start",
    "start": 1577535803541,
    "end": 1577535803967,
    "duration": 426,
    "pid": 7479,
    "index": 0
  },
  {
    "name": "Load Plugin",
    "start": 1577535803543,
    "end": 1577535803548,
    "duration": 5,
    "pid": 7479,
    "index": 1
  },
  {
    "name": "Load Config",
    "start": 1577535803548,
    "end": 1577535803557,
    "duration": 9,
    "pid": 7479,
    "index": 2
  },
  {
    "name": "Require(0) config/config.default.js",
    "start": 1577535803548,
    "end": 1577535803549,
    "duration": 1,
    "pid": 7479,
    "index": 3
  },
  {
    "name": "Require(1) node_modules/egg-session/config/config.default.js",
    "start": 1577535803549,
    "end": 1577535803550,
    "duration": 1,
    "pid": 7479,
    "index": 4
  },
  {
    "name": "Require(2) node_modules/egg-security/config/config.default.js",
    "start": 1577535803550,
    "end": 1577535803550,
    "duration": 0,
    "pid": 7479,
    "index": 5
  },
  {
    "name": "Require(3) node_modules/egg-jsonp/config/config.default.js",
    "start": 1577535803550,
    "end": 1577535803551,
    "duration": 1,
    "pid": 7479,
    "index": 6
  },
  {
    "name": "Require(4) node_modules/egg-onerror/config/config.default.js",
    "start": 1577535803551,
    "end": 1577535803551,
    "duration": 0,
    "pid": 7479,
    "index": 7
  },
  {
    "name": "Require(5) node_modules/egg-i18n/config/config.default.js",
    "start": 1577535803551,
    "end": 1577535803551,
    "duration": 0,
    "pid": 7479,
    "index": 8
  },
  {
    "name": "Require(6) node_modules/egg-watcher/config/config.default.js",
    "start": 1577535803551,
    "end": 1577535803552,
    "duration": 1,
    "pid": 7479,
    "index": 9
  },
  {
    "name": "Require(7) node_modules/egg-schedule/config/config.default.js",
    "start": 1577535803552,
    "end": 1577535803552,
    "duration": 0,
    "pid": 7479,
    "index": 10
  },
  {
    "name": "Require(8) node_modules/egg-multipart/config/config.default.js",
    "start": 1577535803552,
    "end": 1577535803552,
    "duration": 0,
    "pid": 7479,
    "index": 11
  },
  {
    "name": "Require(9) node_modules/egg-development/config/config.default.js",
    "start": 1577535803553,
    "end": 1577535803553,
    "duration": 0,
    "pid": 7479,
    "index": 12
  },
  {
    "name": "Require(10) node_modules/egg-logrotator/config/config.default.js",
    "start": 1577535803553,
    "end": 1577535803553,
    "duration": 0,
    "pid": 7479,
    "index": 13
  },
  {
    "name": "Require(11) node_modules/egg-static/config/config.default.js",
    "start": 1577535803553,
    "end": 1577535803553,
    "duration": 0,
    "pid": 7479,
    "index": 14
  },
  {
    "name": "Require(12) node_modules/egg-view/config/config.default.js",
    "start": 1577535803554,
    "end": 1577535803554,
    "duration": 0,
    "pid": 7479,
    "index": 15
  },
  {
    "name": "Require(13) node_modules/egg-mysql/config/config.default.js",
    "start": 1577535803554,
    "end": 1577535803554,
    "duration": 0,
    "pid": 7479,
    "index": 16
  },
  {
    "name": "Require(14) node_modules/egg-validate/config/config.default.js",
    "start": 1577535803554,
    "end": 1577535803554,
    "duration": 0,
    "pid": 7479,
    "index": 17
  },
  {
    "name": "Require(15) node_modules/egg/config/config.default.js",
    "start": 1577535803555,
    "end": 1577535803555,
    "duration": 0,
    "pid": 7479,
    "index": 18
  },
  {
    "name": "Require(16) config/config.default.js",
    "start": 1577535803556,
    "end": 1577535803556,
    "duration": 0,
    "pid": 7479,
    "index": 19
  },
  {
    "name": "Require(17) node_modules/egg-security/config/config.local.js",
    "start": 1577535803556,
    "end": 1577535803556,
    "duration": 0,
    "pid": 7479,
    "index": 20
  },
  {
    "name": "Require(18) node_modules/egg-watcher/config/config.local.js",
    "start": 1577535803556,
    "end": 1577535803556,
    "duration": 0,
    "pid": 7479,
    "index": 21
  },
  {
    "name": "Require(19) node_modules/egg-view/config/config.local.js",
    "start": 1577535803557,
    "end": 1577535803557,
    "duration": 0,
    "pid": 7479,
    "index": 22
  },
  {
    "name": "Require(20) node_modules/egg/config/config.local.js",
    "start": 1577535803557,
    "end": 1577535803557,
    "duration": 0,
    "pid": 7479,
    "index": 23
  },
  {
    "name": "Load extend/application.js",
    "start": 1577535803558,
    "end": 1577535803564,
    "duration": 6,
    "pid": 7479,
    "index": 24
  },
  {
    "name": "Require(21) node_modules/egg-session/app/extend/application.js",
    "start": 1577535803558,
    "end": 1577535803559,
    "duration": 1,
    "pid": 7479,
    "index": 25
  },
  {
    "name": "Require(22) node_modules/egg-security/app/extend/application.js",
    "start": 1577535803559,
    "end": 1577535803560,
    "duration": 1,
    "pid": 7479,
    "index": 26
  },
  {
    "name": "Require(23) node_modules/egg-jsonp/app/extend/application.js",
    "start": 1577535803560,
    "end": 1577535803561,
    "duration": 1,
    "pid": 7479,
    "index": 27
  },
  {
    "name": "Require(24) node_modules/egg-logrotator/app/extend/application.js",
    "start": 1577535803562,
    "end": 1577535803563,
    "duration": 1,
    "pid": 7479,
    "index": 28
  },
  {
    "name": "Require(25) node_modules/egg-view/app/extend/application.js",
    "start": 1577535803563,
    "end": 1577535803564,
    "duration": 1,
    "pid": 7479,
    "index": 29
  },
  {
    "name": "Load extend/request.js",
    "start": 1577535803565,
    "end": 1577535803566,
    "duration": 1,
    "pid": 7479,
    "index": 30
  },
  {
    "name": "Require(26) node_modules/egg/app/extend/request.js",
    "start": 1577535803565,
    "end": 1577535803566,
    "duration": 1,
    "pid": 7479,
    "index": 31
  },
  {
    "name": "Load extend/response.js",
    "start": 1577535803566,
    "end": 1577535803569,
    "duration": 3,
    "pid": 7479,
    "index": 32
  },
  {
    "name": "Require(27) node_modules/egg/app/extend/response.js",
    "start": 1577535803567,
    "end": 1577535803568,
    "duration": 1,
    "pid": 7479,
    "index": 33
  },
  {
    "name": "Load extend/context.js",
    "start": 1577535803569,
    "end": 1577535803601,
    "duration": 32,
    "pid": 7479,
    "index": 34
  },
  {
    "name": "Require(28) node_modules/egg-security/app/extend/context.js",
    "start": 1577535803569,
    "end": 1577535803578,
    "duration": 9,
    "pid": 7479,
    "index": 35
  },
  {
    "name": "Require(29) node_modules/egg-jsonp/app/extend/context.js",
    "start": 1577535803578,
    "end": 1577535803578,
    "duration": 0,
    "pid": 7479,
    "index": 36
  },
  {
    "name": "Require(30) node_modules/egg-i18n/app/extend/context.js",
    "start": 1577535803579,
    "end": 1577535803579,
    "duration": 0,
    "pid": 7479,
    "index": 37
  },
  {
    "name": "Require(31) node_modules/egg-multipart/app/extend/context.js",
    "start": 1577535803579,
    "end": 1577535803599,
    "duration": 20,
    "pid": 7479,
    "index": 38
  },
  {
    "name": "Require(32) node_modules/egg-view/app/extend/context.js",
    "start": 1577535803599,
    "end": 1577535803600,
    "duration": 1,
    "pid": 7479,
    "index": 39
  },
  {
    "name": "Require(33) node_modules/egg-validate/app/extend/context.js",
    "start": 1577535803600,
    "end": 1577535803600,
    "duration": 0,
    "pid": 7479,
    "index": 40
  },
  {
    "name": "Require(34) node_modules/egg/app/extend/context.js",
    "start": 1577535803600,
    "end": 1577535803600,
    "duration": 0,
    "pid": 7479,
    "index": 41
  },
  {
    "name": "Load extend/helper.js",
    "start": 1577535803601,
    "end": 1577535803623,
    "duration": 22,
    "pid": 7479,
    "index": 42
  },
  {
    "name": "Require(35) node_modules/egg-security/app/extend/helper.js",
    "start": 1577535803601,
    "end": 1577535803621,
    "duration": 20,
    "pid": 7479,
    "index": 43
  },
  {
    "name": "Require(36) node_modules/egg/app/extend/helper.js",
    "start": 1577535803622,
    "end": 1577535803623,
    "duration": 1,
    "pid": 7479,
    "index": 44
  },
  {
    "name": "Load app.js",
    "start": 1577535803624,
    "end": 1577535803662,
    "duration": 38,
    "pid": 7479,
    "index": 45
  },
  {
    "name": "Require(37) node_modules/egg-session/app.js",
    "start": 1577535803624,
    "end": 1577535803624,
    "duration": 0,
    "pid": 7479,
    "index": 46
  },
  {
    "name": "Require(38) node_modules/egg-security/app.js",
    "start": 1577535803625,
    "end": 1577535803626,
    "duration": 1,
    "pid": 7479,
    "index": 47
  },
  {
    "name": "Require(39) node_modules/egg-onerror/app.js",
    "start": 1577535803626,
    "end": 1577535803634,
    "duration": 8,
    "pid": 7479,
    "index": 48
  },
  {
    "name": "Require(40) node_modules/egg-i18n/app.js",
    "start": 1577535803634,
    "end": 1577535803647,
    "duration": 13,
    "pid": 7479,
    "index": 49
  },
  {
    "name": "Require(41) node_modules/egg-watcher/app.js",
    "start": 1577535803647,
    "end": 1577535803649,
    "duration": 2,
    "pid": 7479,
    "index": 50
  },
  {
    "name": "Require(42) node_modules/egg-schedule/app.js",
    "start": 1577535803649,
    "end": 1577535803650,
    "duration": 1,
    "pid": 7479,
    "index": 51
  },
  {
    "name": "Require(43) node_modules/egg-multipart/app.js",
    "start": 1577535803650,
    "end": 1577535803652,
    "duration": 2,
    "pid": 7479,
    "index": 52
  },
  {
    "name": "Require(44) node_modules/egg-development/app.js",
    "start": 1577535803652,
    "end": 1577535803653,
    "duration": 1,
    "pid": 7479,
    "index": 53
  },
  {
    "name": "Require(45) node_modules/egg-logrotator/app.js",
    "start": 1577535803653,
    "end": 1577535803653,
    "duration": 0,
    "pid": 7479,
    "index": 54
  },
  {
    "name": "Require(46) node_modules/egg-static/app.js",
    "start": 1577535803653,
    "end": 1577535803654,
    "duration": 1,
    "pid": 7479,
    "index": 55
  },
  {
    "name": "Require(47) node_modules/egg-mysql/app.js",
    "start": 1577535803654,
    "end": 1577535803660,
    "duration": 6,
    "pid": 7479,
    "index": 56
  },
  {
    "name": "Require(48) node_modules/egg-validate/app.js",
    "start": 1577535803660,
    "end": 1577535803662,
    "duration": 2,
    "pid": 7479,
    "index": 57
  },
  {
    "name": "Before Start in node_modules/egg-watcher/lib/init.js:15:14",
    "start": 1577535803669,
    "end": 1577535803869,
    "duration": 200,
    "pid": 7479,
    "index": 58
  },
  {
    "name": "Before Start in node_modules/egg-mysql/lib/mysql.js:20:7",
    "start": 1577535803754,
    "end": 1577535803967,
    "duration": 213,
    "pid": 7479,
    "index": 59
  },
  {
    "name": "Load Service",
    "start": 1577535803754,
    "end": 1577535803758,
    "duration": 4,
    "pid": 7479,
    "index": 60
  },
  {
    "name": "Load \"service\" to Context",
    "start": 1577535803754,
    "end": 1577535803758,
    "duration": 4,
    "pid": 7479,
    "index": 61
  },
  {
    "name": "Load Middleware",
    "start": 1577535803758,
    "end": 1577535803828,
    "duration": 70,
    "pid": 7479,
    "index": 62
  },
  {
    "name": "Load \"middlewares\" to Application",
    "start": 1577535803758,
    "end": 1577535803820,
    "duration": 62,
    "pid": 7479,
    "index": 63
  },
  {
    "name": "Load Controller",
    "start": 1577535803828,
    "end": 1577535803831,
    "duration": 3,
    "pid": 7479,
    "index": 64
  },
  {
    "name": "Load \"controller\" to Application",
    "start": 1577535803828,
    "end": 1577535803831,
    "duration": 3,
    "pid": 7479,
    "index": 65
  },
  {
    "name": "Load Router",
    "start": 1577535803831,
    "end": 1577535803844,
    "duration": 13,
    "pid": 7479,
    "index": 66
  },
  {
    "name": "Require(49) app/router.js",
    "start": 1577535803831,
    "end": 1577535803840,
    "duration": 9,
    "pid": 7479,
    "index": 67
  },
  {
    "name": "Before Start in node_modules/egg-core/lib/egg.js:303:10",
    "start": 1577535803840,
    "end": 1577535803853,
    "duration": 13,
    "pid": 7479,
    "index": 68
  }
]